optical_multilayer/__about__.py
optical_multilayer/__init__.py
optical_multilayer-0.0.52.dist-info/METADATA
optical_multilayer-0.0.52.dist-info/WHEEL
optical_multilayer-0.0.52.dist-info/licenses/LICENSE.txt
optical_multilayer-0.0.52.dist-info/RECORD
