Metadata-Version: 2.1
Name: optical-multilayer
Version: 0.0.52
Summary: Python module to simulate light behavior in optical multilayers.
Project-URL: Documentation, https://github.com/davidcheson/optical_multilayer_module
Project-URL: Issues, https://github.com/unknown/optical-multilayer/issues
Project-URL: Source, https://github.com/davidcheson/optical_multilayer_module
Author: Jack Liu
Author-email: "David C. Heson" <dch376@msstate.edu>, William Robertson <william.robertson@mtsu.edu>
License-File: LICENSE.txt
Classifier: Development Status :: 2 - Pre-Alpha
Classifier: Programming Language :: Python
Classifier: Programming Language :: Python :: 3.7
Classifier: Programming Language :: Python :: 3.8
Classifier: Programming Language :: Python :: 3.9
Classifier: Programming Language :: Python :: 3.10
Classifier: Programming Language :: Python :: 3.11
Classifier: Programming Language :: Python :: Implementation :: CPython
Classifier: Programming Language :: Python :: Implementation :: PyPy
Requires-Python: >=3.7
Requires-Dist: matplotlib
Requires-Dist: numpy
